yoloair/__init__.py
yoloair/configs/PicoDet/PicoDet-l.yaml
yoloair/configs/PicoDet/PicoDet-m.yaml
yoloair/configs/PicoDet/PicoDet-s.yaml
yoloair/configs/PicoDet/PicoDet-x.yaml
yoloair/configs/attention/yolov5_SOCA.yaml
yoloair/configs/attention/yolov5_ShuffleAttention.yaml
yoloair/configs/attention/yolov5s_CA.yaml
yoloair/configs/attention/yolov5s_CrissCrossAttention.yaml
yoloair/configs/attention/yolov5s_GAMAttention.yaml
yoloair/configs/attention/yolov5s_NAMAttention.yaml
yoloair/configs/attention/yolov5s_S2Attention.yaml
yoloair/configs/attention/yolov5s_SEAttention.yaml
yoloair/configs/attention/yolov5s_SKAttention.yaml
yoloair/configs/attention/yolov5s_SimAM.yaml
yoloair/configs/attention/yolov5s_acmix.yaml
yoloair/configs/attention/yolov5s_cbam.yaml
yoloair/configs/backbone/resnet50-csp.yaml
yoloair/configs/backbone/resnet_x50-csp.yaml
yoloair/configs/backbone/yolov5_RepLKNet.yaml
yoloair/configs/backbone/yolov5_convnext_base.yaml
yoloair/configs/backbone/yolov5_convnext_large.yaml
yoloair/configs/backbone/yolov5_convnext_small.yaml
yoloair/configs/backbone/yolov5_convnext_tiny.yaml
yoloair/configs/backbone/yolov5_convnext_xlarge.yaml
yoloair/configs/backbone/yolov5_efficient.yaml
yoloair/configs/backbone/yolov5_hornet_base.yaml
yoloair/configs/backbone/yolov5_hornet_large.yaml
yoloair/configs/backbone/yolov5_hornet_small.yaml
yoloair/configs/backbone/yolov5_hornet_tiny.yaml
yoloair/configs/backbone/yolov5_hornet_tiny_s.yaml
yoloair/configs/backbone/yolov5_hornet_tiny_xs.yaml
yoloair/configs/backbone/yolov5_hornet_xlarge.yaml
yoloair/configs/backbone/yolov5_mobilenet.yaml
yoloair/configs/backbone/yolov5_mobileone.yaml
yoloair/configs/backbone/yolov5_regnet.yaml
yoloair/configs/backbone/yolov5l-Shffule.yaml
yoloair/configs/head-Improved/yolov5s_asff.yaml
yoloair/configs/head-Improved/yolov5s_asff_ca.yaml
yoloair/configs/head-Improved/yolov5s_decoupled.yaml
yoloair/configs/lightmodels/yolov5-mobile3s.yaml
yoloair/configs/lightmodels/yolov5-mobilev3l.yaml
yoloair-2022.8.23.dist-info/entry_points.txt
yoloair-2022.8.23.dist-info/LICENSE
yoloair-2022.8.23.dist-info/WHEEL
yoloair-2022.8.23.dist-info/METADATA
yoloair-2022.8.23.dist-info/RECORD
