Metadata-Version: 2.1
Name: yoloair
Version: 2022.8.23
Summary: 
Author: iscyy
Maintainer: David Francos
Maintainer-email: me@davidfrancos.net
Requires-Python: >=3.10,<3.11
Classifier: Programming Language :: Python :: 3
Classifier: Programming Language :: Python :: 3.10
Requires-Dist: Pillow (>=7.1.2)
Requires-Dist: PyYAML (>=5.3.1)
Requires-Dist: computation
Requires-Dist: flops (>=0.1.4,<0.2.0)
Requires-Dist: matplotlib (>=3.2.2)
Requires-Dist: numpy (>=1.18.5)
Requires-Dist: opencv-python (>=4.1.2)
Requires-Dist: pandas (>=1.1.4)
Requires-Dist: requests (>=2.23.0)
Requires-Dist: seaborn (>=0.11.0)
Requires-Dist: tensorboard (>=2.4.1)
Requires-Dist: thop (>=0.1.1,<0.2.0)
Requires-Dist: timm (>=0.6.7,<0.7.0)
Requires-Dist: torch (<1.12)
Requires-Dist: torchvision (>=0.8.1)
Requires-Dist: tqdm (>=4.41.0)
